tests/__init__.py
wound_analysis/__init__.py
wound_analysis/cli.py
wound_analysis/dashboard.py
wound_analysis/main.py
wound_analysis/dashboard_components/__init__.py
wound_analysis/dashboard_components/exudate_tab.py
wound_analysis/dashboard_components/impedance_tab.py
wound_analysis/dashboard_components/impedance_tab_original.py
wound_analysis/dashboard_components/llm_analysis_tab.py
wound_analysis/dashboard_components/overview_tab.py
wound_analysis/dashboard_components/oxygenation_tab.py
wound_analysis/dashboard_components/risk_factors_tab.py
wound_analysis/dashboard_components/settings.py
wound_analysis/dashboard_components/temperature_tab.py
wound_analysis/dashboard_components/visualizer.py
wound_analysis/utils/__init__.py
wound_analysis/utils/column_schema.py
wound_analysis/utils/data_processor.py
wound_analysis/utils/llm_interface.py
wound_analysis/utils/statistical_analysis.py
wound_analysis/utils/temp.ipynb
wound_analysis/utils/verify_dataset.py
wound_analysis/utils/logs/all_patients2.pdf
wound_analysis/utils/logs/per_patient2.pdf
wound_analysis-1.5.0.dist-info/METADATA
wound_analysis-1.5.0.dist-info/WHEEL
wound_analysis-1.5.0.dist-info/entry_points.txt
wound_analysis-1.5.0.dist-info/top_level.txt
wound_analysis-1.5.0.dist-info/RECORD
