Metadata-Version: 2.4
Name: wound_analysis
Version: 1.5.0
Summary: Wound Care Analysis System using LLMs and sensor data
Home-page: https://github.com/artinmajdi/wound_EHR_analyzer_private
Author: Artin Majdi
Author-email: msm2024@gmail.com
Keywords: wound care,healthcare,LLM,AI,medical analysis
Classifier: Development Status :: 4 - Beta
Classifier: Intended Audience :: Healthcare Industry
Classifier: License :: Other/Proprietary License
Classifier: Programming Language :: Python :: 3
Classifier: Programming Language :: Python :: 3.10
Classifier: Programming Language :: Python :: 3.11
Classifier: Programming Language :: Python :: 3.12
Classifier: Topic :: Scientific/Engineering :: Medical Science Apps.
Requires-Python: >=3.10
Requires-Dist: Flask>=2.3.0
Requires-Dist: Flask-Cors>=4.0.0
Requires-Dist: Werkzeug>=2.3.0
Requires-Dist: gunicorn>=21.0.0
Requires-Dist: streamlit>=1.32.0
Requires-Dist: watchdog>=2.3.0
Requires-Dist: pandas>=2.1.0
Requires-Dist: numpy>=1.26.0
Requires-Dist: scikit-learn>=1.4.0
Requires-Dist: scipy>=1.12.0
Requires-Dist: openpyxl>=3.1.2
Requires-Dist: xlrd>=2.0.1
Requires-Dist: statsmodels>=0.14.0
Requires-Dist: pydantic>=2.5.0
Requires-Dist: marshmallow>=3.20.0
Requires-Dist: python-dotenv>=1.0.0
Requires-Dist: fastapi>=0.109.0
Requires-Dist: plotly>=5.18.0
Requires-Dist: matplotlib>=3.8.0
Requires-Dist: seaborn>=0.13.0
Requires-Dist: pillow>=10.2.0
Requires-Dist: openai>=1.10.0
Requires-Dist: langchain>=0.1.0
Requires-Dist: langchain-core>=0.1.10
Requires-Dist: langchain-openai>=0.0.5
Requires-Dist: tiktoken>=0.5.0
Requires-Dist: httpx>=0.25.0
Requires-Dist: tenacity>=8.2.0
Requires-Dist: protobuf>=3.20.0
Requires-Dist: sacremoses>=0.0.53
Requires-Dist: python-docx>=0.8.11
Requires-Dist: regex>=2023.10.0
Requires-Dist: jinja2>=3.1.0
Requires-Dist: pathlib>=1.0.1
Requires-Dist: pytest>=7.4.0
Requires-Dist: requests>=2.31.0
Requires-Dist: pytest-cov>=4.1.0
Requires-Dist: tqdm>=4.66.0
Requires-Dist: colorama>=0.4.6
Requires-Dist: rich>=13.6.0
Dynamic: author
Dynamic: author-email
Dynamic: classifier
Dynamic: description
Dynamic: description-content-type
Dynamic: home-page
Dynamic: keywords
Dynamic: requires-dist
Dynamic: requires-python
Dynamic: summary
